playwright_html_renderer/__init__.py
playwright_html_renderer/__main__.py
playwright_html_renderer/cli.py
playwright_html_renderer-0.3.dist-info/LICENSE
playwright_html_renderer-0.3.dist-info/METADATA
playwright_html_renderer-0.3.dist-info/WHEEL
playwright_html_renderer-0.3.dist-info/entry_points.txt
playwright_html_renderer-0.3.dist-info/top_level.txt
playwright_html_renderer-0.3.dist-info/RECORD
