Metadata-Version: 2.1
Name: playwright-html-renderer
Version: 0.3
Summary: CLI tool to render HTML using Playwright
Home-page: https://github.com/custom-packages/playwright-html-renderer
Author: Stefan Kühnel
License: European Union Public License 1.2
Project-URL: Documentation, https://github.com/custom-packages/playwright-html-renderer
Project-URL: Source code, https://github.com/custom-packages/playwright-html-renderer
Project-URL: Issues, https://github.com/custom-packages/playwright-html-renderer/issues
Project-URL: CI, https://github.com/custom-packages/playwright-html-renderer/actions
Classifier: Development Status :: 2 - Pre-Alpha
Classifier: Intended Audience :: Developers
Classifier: Intended Audience :: End Users/Desktop
Classifier: Intended Audience :: Information Technology
Classifier: License :: OSI Approved :: European Union Public Licence 1.2 (EUPL 1.2)
Classifier: Natural Language :: English
Classifier: Programming Language :: Python :: 3.8
Classifier: Programming Language :: Python :: 3.9
Classifier: Programming Language :: Python :: 3.10
Classifier: Programming Language :: Python :: 3.11
Classifier: Programming Language :: Python :: 3.12
Classifier: Programming Language :: Python :: 3.13
Classifier: Topic :: Internet :: WWW/HTTP :: Browsers
Requires-Python: >=3.8
License-File: LICENSE
Requires-Dist: playwright ==1.44.0
